deltacat/__init__.py
deltacat/annotations.py
deltacat/api.py
deltacat/constants.py
deltacat/env.py
deltacat/exceptions.py
deltacat/logs.py
deltacat/aws/__init__.py
deltacat/aws/clients.py
deltacat/aws/constants.py
deltacat/aws/s3u.py
deltacat/benchmarking/__init__.py
deltacat/benchmarking/benchmark_engine.py
deltacat/benchmarking/benchmark_parquet_reads.py
deltacat/benchmarking/benchmark_report.py
deltacat/benchmarking/benchmark_suite.py
deltacat/benchmarking/conftest.py
deltacat/benchmarking/test_benchmark_pipeline.py
deltacat/benchmarking/data/__init__.py
deltacat/benchmarking/data/random_row_generator.py
deltacat/benchmarking/data/row_generator.py
deltacat/catalog/__init__.py
deltacat/catalog/delegate.py
deltacat/catalog/interface.py
deltacat/catalog/main/__init__.py
deltacat/catalog/main/impl.py
deltacat/catalog/model/__init__.py
deltacat/catalog/model/catalog.py
deltacat/catalog/model/properties.py
deltacat/catalog/model/table_definition.py
deltacat/compute/__init__.py
deltacat/compute/janitor.py
deltacat/compute/compactor/__init__.py
deltacat/compute/compactor/compaction_session.py
deltacat/compute/compactor/repartition_session.py
deltacat/compute/compactor/model/__init__.py
deltacat/compute/compactor/model/compact_partition_params.py
deltacat/compute/compactor/model/compaction_session_audit_info.py
deltacat/compute/compactor/model/compactor_version.py
deltacat/compute/compactor/model/dedupe_result.py
deltacat/compute/compactor/model/delta_annotated.py
deltacat/compute/compactor/model/delta_file_envelope.py
deltacat/compute/compactor/model/delta_file_locator.py
deltacat/compute/compactor/model/hash_bucket_result.py
deltacat/compute/compactor/model/materialize_result.py
deltacat/compute/compactor/model/primary_key_index.py
deltacat/compute/compactor/model/pyarrow_write_result.py
deltacat/compute/compactor/model/repartition_result.py
deltacat/compute/compactor/model/round_completion_info.py
deltacat/compute/compactor/model/table_object_store.py
deltacat-2.0.0.post4.dist-info/licenses/LICENSE
deltacat-2.0.0.post4.dist-info/METADATA
deltacat-2.0.0.post4.dist-info/WHEEL
deltacat-2.0.0.post4.dist-info/top_level.txt
deltacat-2.0.0.post4.dist-info/RECORD
