Metadata-Version: 2.4
Name: deltacat
Version: 2.0.0.post4
Summary: DeltaCAT is a portable Pythonic Data Lakehouse powered by Ray.
Home-page: https://github.com/ray-project/deltacat
Author: Ray Team
Classifier: Development Status :: 4 - Beta
Classifier: Intended Audience :: Developers
Classifier: Programming Language :: Python :: 3 :: Only
Classifier: Programming Language :: Python :: 3.10
Classifier: Programming Language :: Python :: 3.9
Classifier: Operating System :: OS Independent
Requires-Python: >=3.9
License-File: LICENSE
Requires-Dist: aws-embedded-metrics==3.2.0
Requires-Dist: boto3~=1.34
Requires-Dist: google-cloud-storage
Requires-Dist: gcsfs==2025.3.2
Requires-Dist: daft==0.4.15
Requires-Dist: intervaltree==3.1.0
Requires-Dist: numpy==1.22.4
Requires-Dist: pandas==2.2.3
Requires-Dist: polars==1.28.1
Requires-Dist: pyarrow==16.0.0
Requires-Dist: pydantic!=2.0.*,!=2.1.*,!=2.2.*,!=2.3.*,!=2.4.*,<3
Requires-Dist: pymemcache==4.0.0
Requires-Dist: ray[default]==2.46.0
Requires-Dist: tenacity==8.2.3
Requires-Dist: typing-extensions==4.6.1
Requires-Dist: redis==5.0.0
Requires-Dist: schedule==1.2.0
Provides-Extra: iceberg
Requires-Dist: pyiceberg[glue]>=0.9.0; extra == "iceberg"
Requires-Dist: pyiceberg[hive]>=0.9.0; extra == "iceberg"
Requires-Dist: pyiceberg[sql-sqlite]>=0.9.0; extra == "iceberg"
Provides-Extra: beam
Requires-Dist: apache-beam==2.65.0; extra == "beam"
Provides-Extra: s3fs
Requires-Dist: s3fs==2025.3.2; extra == "s3fs"
Dynamic: author
Dynamic: classifier
Dynamic: description
Dynamic: description-content-type
Dynamic: home-page
Dynamic: license-file
Dynamic: provides-extra
Dynamic: requires-dist
Dynamic: requires-python
Dynamic: summary
